[
    {
        "id": "11",
        "username": "test5",
        "company": null,
        "fname": "John",
        "lname": "Smith",
        "email": "test5@example.com",
        "password": "$2y$10$nh9vlQPAhajYL3uxxTwNVeXxZitHbjY97MOIzGrPAhObMJKJqxRPy",
        "created_at": "2015-05-25 18:21:45",
        "updated_at": "2015-10-07 10:57:09",
        "remember_token": "iTOr0XSZ54TYSKhDLpZ6BSZf5xvYPgKbsFLrMk8BHl8iz7kcmGrJVKTK8A6B",
        "confirmed": "1",
        "confirmation_code": null
    },
    {
        "id": "12",
        "username": "test6",
        "company": null,
        "fname": "",
        "lname": "",
        "email": "test6@example.com",
        "password": "$2y$10$otA\/jvvWQNxfI2JKoqGbQ.b3FdtXYnZ40dKTIBWXACJCfWE5W5eJy",
        "created_at": "2015-05-25 19:47:06",
        "updated_at": "2015-11-01 13:26:52",
        "remember_token": "H9C7dEN0fdovEBqwYCZkoHIPwWAfXDY7z5lUwzQZTtefselbmyQSZZ36X3bl",
        "confirmed": "1",
        "confirmation_code": null
    },
    {
        "id": "14",
        "username": "test8",
        "company": null,
        "fname": "",
        "lname": "",
        "email": "test8@example.com",
        "password": "$2y$10$xZ2U7IiRUC.bi3Xz2z8I3eC2SOmFKQ9NezXrSDi11gfZYUgcgQ9rO",
        "created_at": "2015-05-25 20:40:21",
        "updated_at": "2015-06-07 22:39:05",
        "remember_token": "ksVRmVPKcZOHtVRgO1vz5EWbMKRnZgB7DKVvRJINIbgCjC0ucUqXNrRLcqgp",
        "confirmed": "1",
        "confirmation_code": null
    },
    {
        "id": "15",
        "username": "test9",
        "company": null,
        "fname": "",
        "lname": "",
        "email": "test9@example.com",
        "password": "$2y$10$c\/TooAwZy\/GGmPUfd6vgz.CzazxJs0NXXazjEYWrQLWKHAaejyTGq",
        "created_at": "2015-06-09 20:02:23",
        "updated_at": "2015-11-01 02:17:26",
        "remember_token": "44QhQGVzZ7tfJ4AhGXm7NkQh4lT6kE7UCuC1AWbAz5bUxbd8sjC4wkhApdG2",
        "confirmed": "1",
        "confirmation_code": null
    },
    {
        "id": "16",
        "username": "test10",
        "company": null,
        "fname": "",
        "lname": "",
        "email": "test10@example.com",
        "password": "$2y$10$eFXEI8Df5LaNjkN6b2PZ7OGYw2OrNbiNvpIY1HgxCRUQfMXSp9OZ6",
        "created_at": "2015-06-14 16:54:41",
        "updated_at": "2015-07-28 21:41:31",
        "remember_token": "QScvqgP5ko4tdqDmG5lFumsJC7VcjZlAABDxJ6PyO2RGZUup4l25AnSBR8m5",
        "confirmed": "1",
        "confirmation_code": null
    },
    {
        "id": "21",
        "username": "coke",
        "company": "Coke",
        "fname": "Jack",
        "lname": "Milton",
        "email": "jack@coke.com",
        "password": "$2y$10$pl39xGkGVoE08a2aQqT3keWAujx7ag0rkIOmwisUYog0l0Q3uJH7K",
        "created_at": "2015-06-15 00:03:54",
        "updated_at": "2015-07-29 21:53:46",
        "remember_token": "noGHYSE5h86IiV70J7bURSGZ6QWV7GLetEvKc2k4gh7VnkT5Y2FkwnxVdoBw",
        "confirmed": "1",
        "confirmation_code": null
    },
    {
        "id": "22",
        "username": "test11",
        "company": null,
        "fname": "Mark",
        "lname": "Jacob",
        "email": "test11@example.com",
        "password": "$2y$10$Y2OX8qxYCQRAcn3cSc8oFeN2MbV\/Kdg7YyvQFsxR2gh\/vBoCCIEXy",
        "created_at": "2015-06-15 00:16:21",
        "updated_at": "2015-07-29 21:36:26",
        "remember_token": "BWnoprqdS9EpT2UiBuB53IaFkA97RpfAXellGkZ0AB2gDBAp4NhWtFMlJzuv",
        "confirmed": "1",
        "confirmation_code": null
    },
    {
        "id": "35",
        "username": "test15",
        "company": null,
        "fname": "Hello",
        "lname": "World",
        "email": "test15@example.com",
        "password": "$2y$10$FWGvWlAelYn5UG.KVWKjc.L6pJf8rGTDBeeR7hFuAUdf1iX2Z8S6q",
        "created_at": "2015-06-23 22:33:55",
        "updated_at": "2015-07-29 21:35:13",
        "remember_token": "GvYHsMwSoA4SuCqSlGe4Go7G7qHyceuspFd6GtE3qjwVyYCcLfw0KnR5oXJE",
        "confirmed": "1",
        "confirmation_code": null
    },
    {
        "id": "36",
        "username": "test16",
        "company": "test16",
        "fname": "test",
        "lname": "ad",
        "email": "test16@example.com",
        "password": "$2y$10$nxpP\/yr5NHmkgHlbRD4KTevE4RTzTUhY.3s\/LAKRfOhCCvrlulcfG",
        "created_at": "2015-06-23 22:35:33",
        "updated_at": "2015-09-09 14:35:01",
        "remember_token": "gBgSR8hdPehjEplhyR2Z8c5Po7KoAJQblPeC8kXNjYh276nw421Ri5z405OZ",
        "confirmed": "1",
        "confirmation_code": null
    },
    {
        "id": "38",
        "username": "jackymoon",
        "company": null,
        "fname": "jacky",
        "lname": "moon",
        "email": "jackymoon@example.com",
        "password": "$2y$10$rDTs.mXC3B53emIqZCkRsOxS7GbBQ.Ozqm\/zCmnS902hHw\/uexd4a",
        "created_at": "2015-06-24 19:31:47",
        "updated_at": "2015-08-25 14:14:54",
        "remember_token": "QSErp7LhWn1UImZGZ5fnolxvd2DR87TuujtHCVzcl1pJK81Ep1LVfBDUu79F",
        "confirmed": "1",
        "confirmation_code": null
    },
    {
        "id": "39",
        "username": "test2333",
        "company": null,
        "fname": "Test",
        "lname": "test",
        "email": "test2333@example.com",
        "password": "$2y$10$BcMxshov1WQsuBCR2UxIl.UHjA7dfK6x2TNhGHTOFL8o9SmqdQ2Q2",
        "created_at": "2015-11-01 00:34:27",
        "updated_at": "2015-11-01 00:35:33",
        "remember_token": "jcVKkGpuGwnMLxOGKH3ZLXSkLQTRvB1zeQGT5yZRIIoPtSZ8TOeS3dLBuYwO",
        "confirmed": "1",
        "confirmation_code": ""
    },
    {
        "id": "41",
        "username": "test999",
        "company": null,
        "fname": "test",
        "lname": "test",
        "email": "test999@example.com",
        "password": "$2y$10$gAK6YekZgIyfS3qBx0d1gu3wqyuWMj1u20p1PNNHlj.RTNxMrbi4y",
        "created_at": "2015-11-01 01:08:44",
        "updated_at": "2015-11-01 01:08:44",
        "remember_token": null,
        "confirmed": "0",
        "confirmation_code": "Y9Qxksyeg0HxIINWvfLmkj399ZEwnP"
    },
    {
        "id": "42",
        "username": "test108",
        "company": null,
        "fname": "test",
        "lname": "w",
        "email": "test108@example.com",
        "password": "$2y$10$RRCB4yAIAdIuD\/upBayh\/e7gkfhz0LoOK8Uio4KS4R5ZvpR3SVQFK",
        "created_at": "2015-11-01 01:09:57",
        "updated_at": "2015-11-01 01:09:57",
        "remember_token": null,
        "confirmed": "0",
        "confirmation_code": "XwkoK5qBnDvPKYM2ylP4ccXy8xadSV"
    },
    {
        "id": "43",
        "username": "testbrand",
        "company": null,
        "fname": "test",
        "lname": "test",
        "email": "testbrand@example.com",
        "password": "$2y$10$g2S8y6U1lgWdNwdDZhHDpeOUlRHAirnnc2jZmmttyTloYQwXTsviW",
        "created_at": "2015-11-01 01:10:45",
        "updated_at": "2015-11-01 01:10:45",
        "remember_token": null,
        "confirmed": "0",
        "confirmation_code": "p2TcX4QZ4dMoaIhP8GpoCIygrJGt5B"
    },
    {
        "id": "44",
        "username": "testbrand2",
        "company": null,
        "fname": "test",
        "lname": "test",
        "email": "testbrand2@example.com",
        "password": "$2y$10$Ngn9beryCJxUgIHhUo5d8uvZYnni4totA7x30az9ctu0aWgtEasG6",
        "created_at": "2015-11-01 01:14:15",
        "updated_at": "2015-11-01 01:14:15",
        "remember_token": null,
        "confirmed": "0",
        "confirmation_code": "H6Iegyg4IY3hsUTOVZp4rFD3DFjZmd"
    },
    {
        "id": "45",
        "username": "testbrand3",
        "company": null,
        "fname": "test",
        "lname": "t",
        "email": "testbrand3@example.com",
        "password": "$2y$10$WrhFFZ8sPIUOL6Mcm7EBIusZy0RSTjITA9FCK.EUa6fqsZ7ZB1hLu",
        "created_at": "2015-11-01 01:17:53",
        "updated_at": "2015-11-01 01:17:53",
        "remember_token": null,
        "confirmed": "0",
        "confirmation_code": "SIf9JBmOzbhrDMRFKKZA9IHPCUFQjd"
    },
    {
        "id": "46",
        "username": "test606",
        "company": null,
        "fname": "test",
        "lname": "test",
        "email": "test606@example.com",
        "password": "$2y$10$3L2nPtdpcwf1AfFc95o2pu5W7VXJMuaXZGafVFldkRlz5iMc3sloy",
        "created_at": "2015-11-01 01:52:39",
        "updated_at": "2015-11-01 01:52:39",
        "remember_token": null,
        "confirmed": "0",
        "confirmation_code": "nCfyV5n0qbsD2iT8lWclxcabW93I1F"
    }
]